<?xml version='1.0' encoding='utf-8'?>
<contents xmlns:scripture="https://github.com/amarthwen/sword/xmlns/scripture" xmlns:sectioning="https://github.com/amarthwen/sword/xmlns/sectioning"><sectioning:document><object><text>Dwaj Świadkowie:</text></object><object><scripture:extract origin="Obj 11, 3" translation="BW"><line id="30902" origin="Obj 11, 3">I dam dwom moim świadkom moc, i będą, odziani w wory, prorokowali przez tysiąc dwieście sześćdziesiąt dni.</line></scripture:extract></object><object><text>Dwa Drzewa Oliwne:</text></object><object><scripture:extract origin="Obj 11, 4" translation="BW"><line id="30903" origin="Obj 11, 4">Oni to są dwoma drzewami oliwnymi i dwoma świecznikami, które stoją przed Panem ziemi.</line></scripture:extract></object><object><scripture:extract origin="Za 4, 11" translation="BW"><line id="22998" origin="Za 4, 11">Wtedy odezwałem się i zapytałem go: Co oznaczają te dwa drzewa oliwne po prawej i lewej stronie świecznika?</line></scripture:extract></object><object><text>Dwa Świeczniki:</text></object><object><scripture:extract origin="Obj 11, 4" translation="BW"><line id="30903" origin="Obj 11, 4">Oni to są dwoma drzewami oliwnymi i dwoma świecznikami, które stoją przed Panem ziemi.</line></scripture:extract></object><object><text>Dwaj Prorocy:</text></object><object><scripture:extract origin="Obj 11, 10" translation="BW"><line id="30909" origin="Obj 11, 10">A mieszkańcy ziemi radować się będą nimi i weselić się, i podarunki sobie nawzajem posyłać, dlatego że ci dwaj prorocy udręczyli mieszkańców ziemi.</line></scripture:extract></object><object><text>Dwaj Pomazańcy:</text></object><object><scripture:extract origin="Za 4, 11-14" translation="BW"><line id="22998" origin="Za 4, 11">Wtedy odezwałem się i zapytałem go: Co oznaczają te dwa drzewa oliwne po prawej i lewej stronie świecznika?</line><line id="22999" origin="Za 4, 12">I powtórnie odezwałem się, i zapytałem go: Co oznaczają te dwie gałązki drzew oliwnych, które dwiema złotymi rurkami wypuszczają z siebie oliwę do złotych lamp?</line><line id="23000" origin="Za 4, 13">Wtedy on odpowiedział mi: Czy nie wiesz, co one oznaczają? I odpowiedziałem: Nie, mój panie!</line><line id="23001" origin="Za 4, 14">A on odrzekł: To są dwaj pomazańcy, którzy stoją przed Panem całej ziemi.</line></scripture:extract></object><object><scripture:extract origin="Ps 105, 6-15" translation="BW"><line id="15674" origin="Ps 105, 6">Wy, potomkowie Abrahama, sługi jego, Synowie Jakuba, wybrańcy jego!</line><line id="15675" origin="Ps 105, 7">On jest Panem, Bogiem waszym, Prawa jego na całej ziemi.</line><line id="15676" origin="Ps 105, 8">Pamięta wiecznie o przymierzu swoim, O słowie, które dał tysiącznym pokoleniom,</line><line id="15677" origin="Ps 105, 9">O przymierzu, które zawarł z Abrahamem, I o przysiędze swej dla Izaaka.</line><line id="15678" origin="Ps 105, 10">Ustanowił je dla Jakuba jako prawo, Dla Izraela jako przymierze wieczne,</line><line id="15679" origin="Ps 105, 11">Mówiąc: Tobie dam ziemię Kanaan, W dziedziczne wasze posiadanie.</line><line id="15680" origin="Ps 105, 12">Gdy było ich jeszcze niewielu, Nieliczni i obcy w niej,</line><line id="15681" origin="Ps 105, 13">Wędrowali wtedy od narodu do narodu, Z jednego królestwa do innego ludu.</line><line id="15682" origin="Ps 105, 14">Nikomu nie dozwolił ich krzywdzić I z powodu nich karał nawet królów:</line><line id="15683" origin="Ps 105, 15">Nie tykajcie pomazańców moich I nie czyńcie nic złego prorokom moim!</line></scripture:extract></object><object><text>Pomazaniec:</text></object><object><scripture:extract origin="Ps 20, 1-10" translation="BW"><line id="14192" origin="Ps 20, 1">Przewodnikowi chóru. Psalm Dawidowy.</line><line id="14193" origin="Ps 20, 2">Niech cię wysłucha Pan w dniu utrapienia, Niech cię wzmocni imię Boga Jakubowego!</line><line id="14194" origin="Ps 20, 3">Niech ci ześle pomoc ze świątyni I niech cię wesprze z Syjonu!</line><line id="14195" origin="Ps 20, 4">Niechaj wspomni wszystkie dary twoje I niech przyjmie całopalenia twoje. Sela.</line><line id="14196" origin="Ps 20, 5">Niech ci da to, czego pragnie serce twoje, I niech wypełni każdy twój zamysł!</line><line id="14197" origin="Ps 20, 6">Będziemy się weselić ze zwycięstwa twego I w imię Boga naszego wzniesiemy sztandary! Niech Pan spełni wszystkie prośby twoje!</line><line id="14198" origin="Ps 20, 7">Teraz wiem, że Pan wybawił pomazańca swego. Wysłucha go z nieba swego świętego Przez potężną pomoc prawicy swojej.</line><line id="14199" origin="Ps 20, 8">Jedni chlubią się wozami, drudzy końmi, Lecz my chlubimy się imieniem Pana, Boga naszego.</line><line id="14200" origin="Ps 20, 9">Zadrżały im kolana i upadli, Lecz my stoimy i trwamy.</line><line id="14201" origin="Ps 20, 10">Panie, królu nasz, pomóż! Wysłuchaj nas w dniu wołania naszego.</line></scripture:extract></object><object><scripture:extract origin="Ha 3, 3-4.10-13" translation="BW"><line id="22836" origin="Ha 3, 3">Bóg przychodzi z Temanu, Święty z góry Paran. Sela. Jego wspaniałość okrywa niebiosa, a ziemia jest pełna jego chwały.</line><line id="22837" origin="Ha 3, 4">Pod nim jest blask jak światłość, promienie wychodzą z jego rąk i tam jest ukryta jego moc.</line><line id="22843" origin="Ha 3, 10">Na twój widok drżą góry obłoki spuszczają ulewne deszcze; otchłań morska wydaje swój głos, wysoko podnosi swe ramiona.</line><line id="22844" origin="Ha 3, 11">Słońce i księżyc wstrzymały swoją jasność w świetle twych szybkich strzał, w blasku twojej lśniącej włóczni.</line><line id="22845" origin="Ha 3, 12">W zawziętości kroczysz po ziemi, w gniewie depczesz narody.</line><line id="22846" origin="Ha 3, 13">Wyruszasz na pomoc swojemu ludowi, aby ratować swojego pomazańca. Rozbijasz dom bezbożnego, obnażasz fundamenty aż do skały. Sela.</line></scripture:extract></object></sectioning:document></contents>