<?xml version='1.0' encoding='utf-8'?>
<document:document xmlns:document="https://github.com/amarthwen/sword/xmlns/document" xmlns:object="https://github.com/amarthwen/sword/xmlns/object" xmlns:scripture="https://github.com/amarthwen/sword/xmlns/scripture" xmlns:sectioning="https://github.com/amarthwen/sword/xmlns/sectioning"><document:config emblem="default.jpg" /><document:body><object:paragraph><sectioning:section level="0"><sectioning:section level="1" title="Temat główny"><object:paragraph><scripture:extract translation="BW" normalized="Hbr 12, 22-24" origin="Hbr 12, 22-24" inline="false"><verset ref="30274..30276" origin="Hbr 12, 22-24" /></scripture:extract></object:paragraph><object:paragraph><scripture:extract translation="BW" normalized="Hbr 13, 20-21" origin="Hbr 13, 20-21" inline="false"><verset ref="30301..30302" origin="Hbr 13, 20-21" /></scripture:extract></object:paragraph><object:paragraph><scripture:extract translation="BW" normalized="Rz 8, 8-11" origin="Rz 8, 8-11" inline="false"><verset ref="28165..28168" origin="Rz 8, 8-11" /></scripture:extract></object:paragraph><object:paragraph><scripture:extract translation="BW" normalized="Mt 26, 27-28" origin="Mt 26, 27-28" inline="false"><verset ref="24146..24147" origin="Mt 26, 27-28" /></scripture:extract></object:paragraph><object:paragraph><scripture:extract translation="BW" normalized="J 4, 7-15" origin="J 4, 7-15" inline="false"><verset ref="26205..26213" origin="J 4, 7-15" /></scripture:extract></object:paragraph><object:paragraph><scripture:extract translation="BW" normalized="J 7, 37-39" origin="J 7, 37-39" inline="false"><verset ref="26407..26409" origin="J 7, 37-39" /></scripture:extract></object:paragraph><object:paragraph><scripture:extract translation="BW" normalized="Ef 2, 11-13" origin="Ef 2, 11-13" inline="false"><verset ref="29280..29282" origin="Ef 2, 11-13" /></scripture:extract></object:paragraph></sectioning:section></sectioning:section></object:paragraph></document:body></document:document>