<?xml version='1.0' encoding='utf-8'?>
<contents xmlns:scripture="https://github.com/amarthwen/sword/xmlns/scripture" xmlns:sectioning="https://github.com/amarthwen/sword/xmlns/sectioning"><sectioning:document><object><scripture:extract origin="2 Kor 1, 21-22" translation="BW"><verset origin="2Kor 1, 21-22" ref="28849..28850" /></scripture:extract></object><object><scripture:extract origin="Rz 8, 9" translation="BW"><verset origin="Rz 8, 9" ref="28153" /></scripture:extract></object><object><scripture:extract origin="Ef 1, 13" translation="BW"><verset origin="Ef 1, 13" ref="29246" /></scripture:extract></object><object><scripture:extract origin="Rz 8, 14" translation="BW"><verset origin="Rz 8, 14" ref="28158" /></scripture:extract></object><object><scripture:extract origin="Ef 4, 30" translation="BW"><verset origin="Ef 4, 30" ref="29329" /></scripture:extract></object></sectioning:document></contents>