<?xml version='1.0' encoding='utf-8'?>
<document:document xmlns:document="https://github.com/amarthwen/sword/xmlns/document" xmlns:object="https://github.com/amarthwen/sword/xmlns/object" xmlns:scripture="https://github.com/amarthwen/sword/xmlns/scripture" xmlns:sectioning="https://github.com/amarthwen/sword/xmlns/sectioning"><document:config emblem="default.jpg" /><document:body><object:paragraph><sectioning:section level="0"><sectioning:section level="1" title="Temat główny"><object:paragraph><scripture:extract translation="BW" normalized="Dn 8, 11-14" origin="Dn 8, 11-14" inline="false"><verset ref="22039..22042" origin="Dn 8, 11-14" /></scripture:extract></object:paragraph><object:paragraph><scripture:extract translation="BW" normalized="Dn 11, 31" origin="Dn 11, 31" inline="false"><verset ref="22134" origin="Dn 11, 31" /></scripture:extract></object:paragraph><object:paragraph><scripture:extract translation="BW" normalized="Dn 12, 11-12" origin="Dn 12, 11-12" inline="false"><verset ref="22159..22160" origin="Dn 12, 11-12" /></scripture:extract></object:paragraph><object:paragraph><scripture:extract translation="BW" normalized="Jl 1, 4-10" origin="Jl 1, 4-10" inline="false"><verset ref="22362..22368" origin="Jl 1, 4-10" /></scripture:extract></object:paragraph><object:paragraph><scripture:extract translation="BW" normalized="Obj 9, 1-8" origin="Obj 9, 1-8" inline="false"><verset ref="30882..30889" origin="Obj 9, 1-8" /></scripture:extract></object:paragraph><object:paragraph><scripture:extract translation="BW" normalized="Am 4, 9" origin="Am 4, 9" inline="false"><verset ref="22486" origin="Am 4, 9" /></scripture:extract></object:paragraph><object:paragraph><scripture:extract translation="BW" normalized="Mt 24, 15-16.21-22.29-30" origin="Mt 24, 15-16.21-22.29-30" inline="false"><verset ref="24037..24038" origin="Mt 24, 15-16" /><verset ref="24043..24044" origin="Mt 24, 21-22" /><verset ref="24051..24052" origin="Mt 24, 29-30" /></scripture:extract></object:paragraph><object:paragraph><scripture:extract translation="BW" normalized="Jl 2, 12-14" origin="Jl 2, 12-14" inline="false"><verset ref="22390..22392" origin="Jl 2, 12-14" /></scripture:extract></object:paragraph><object:paragraph><scripture:extract translation="BW" normalized="1Kor 10, 19-21" origin="1 Kor 10, 19-21" inline="false"><verset ref="28627..28629" origin="1Kor 10, 19-21" /></scripture:extract></object:paragraph><object:paragraph><scripture:extract translation="BW" normalized="1Kor 6, 15-20" origin="1 Kor 6, 15-20" inline="false"><verset ref="28523..28528" origin="1Kor 6, 15-20" /></scripture:extract></object:paragraph><object:paragraph><scripture:extract translation="BW" normalized="Jl 1, 1-20" origin="Jl 1, 1-20" inline="false"><verset ref="22359..22378" origin="Jl 1, 1-20" /></scripture:extract></object:paragraph><object:paragraph><scripture:extract translation="BW" normalized="Iz 6, 8-13" origin="Iz 6, 8-13" inline="false"><verset ref="17844..17849" origin="Iz 6, 8-13" /></scripture:extract></object:paragraph><object:paragraph><scripture:extract translation="BW" normalized="Iz 24, 3" origin="Iz 24, 3" inline="false"><verset ref="18165" origin="Iz 24, 3" /></scripture:extract></object:paragraph><object:paragraph><scripture:extract translation="BW" normalized="Jr 16, 18" origin="Jr 16, 18" inline="false"><verset ref="19421" origin="Jr 16, 18" /></scripture:extract></object:paragraph><object:paragraph><scripture:extract translation="BW" normalized="Iz 44, 9-20" origin="Iz 44, 9-20" inline="false"><verset ref="18609..18620" origin="Iz 44, 9-20" /></scripture:extract></object:paragraph><object:paragraph><scripture:extract translation="BW" normalized="Jr 7, 30" origin="Jr 7, 30" inline="false"><verset ref="19216" origin="Jr 7, 30" /></scripture:extract></object:paragraph><object:paragraph><scripture:extract translation="BW" normalized="Dn 9, 27" origin="Dn 9, 27" inline="false"><verset ref="22082" origin="Dn 9, 27" /></scripture:extract></object:paragraph><object:paragraph><scripture:extract translation="BW" normalized="Obj 14, 11-12" origin="Obj 14, 11-12" inline="false"><verset ref="30979..30980" origin="Obj 14, 11-12" /></scripture:extract></object:paragraph><object:paragraph><scripture:extract translation="BW" normalized="Jr 15, 14" origin="Jr 15, 14" inline="false"><verset ref="19396" origin="Jr 15, 14" /></scripture:extract></object:paragraph><object:paragraph><scripture:extract translation="BW" normalized="Jr 16, 13" origin="Jr 16, 13" inline="false"><verset ref="19416" origin="Jr 16, 13" /></scripture:extract></object:paragraph><object:paragraph><scripture:extract translation="BW" normalized="Jr 17, 4" origin="Jr 17, 4" inline="false"><verset ref="19428" origin="Jr 17, 4" /></scripture:extract></object:paragraph><object:paragraph><scripture:extract translation="BW" normalized="Ez 28, 18" origin="Ez 28, 18" inline="false"><verset ref="21242" origin="Ez 28, 18" /></scripture:extract></object:paragraph><object:paragraph><scripture:extract translation="BW" normalized="1Kor 10, 19-20" origin="1 Kor 10, 19-20" inline="false"><verset ref="28627..28628" origin="1Kor 10, 19-20" /></scripture:extract></object:paragraph></sectioning:section></sectioning:section></object:paragraph></document:body></document:document>